nanodlna/__init__.py
nanodlna/cli.py
nanodlna/devices.py
nanodlna/dlna.py
nanodlna/streaming.py
nanodlna/templates/action-Play.xml
nanodlna/templates/action-SetAVTransportURI.xml
nanodlna/templates/metadata-example1.xml
nanodlna/templates/metadata-video_subtitle.xml
nanodlna-0.2.1.dist-info/LICENSE
nanodlna-0.2.1.dist-info/METADATA
nanodlna-0.2.1.dist-info/WHEEL
nanodlna-0.2.1.dist-info/entry_points.txt
nanodlna-0.2.1.dist-info/top_level.txt
nanodlna-0.2.1.dist-info/zip-safe
nanodlna-0.2.1.dist-info/RECORD
